cwbtasks/__init__.py
cwbtasks/__main__.py
cwbtasks/api.py
cwbtasks/cli.py
cwbtasks/db.py
cwbtasks-0.0.1.dist-info/entry_points.txt
cwbtasks-0.0.1.dist-info/LICENSE
cwbtasks-0.0.1.dist-info/WHEEL
cwbtasks-0.0.1.dist-info/METADATA
cwbtasks-0.0.1.dist-info/RECORD
